pyopenacoustics.py
pyopenacoustics-1.0.0a3.dist-info/METADATA
pyopenacoustics-1.0.0a3.dist-info/RECORD
pyopenacoustics-1.0.0a3.dist-info/WHEEL
pyopenacoustics-1.0.0a3.dist-info/top_level.txt
